{
  "timestamp": "2025-11-01T23:37:13.725594",
  "image_shape": {
    "height": 480,
    "width": 640,
    "channels": 3
  },
  "num_persons_detected": 1,
  "persons": [
    {
      "person_id": 0,
      "keypoints": [
        {
          "name": "nose",
          "x": 111.81278228759766,
          "y": 195.26837158203125,
          "confidence": 0.9722278118133545,
          "visible": true
        },
        {
          "name": "left_eye",
          "x": 114.86994934082031,
          "y": 183.0,
          "confidence": 0.9872855544090271,
          "visible": true
        },
        {
          "name": "right_eye",
          "x": 107.57794189453125,
          "y": 184.31869506835938,
          "confidence": 0.5894169807434082,
          "visible": true
        },
        {
          "name": "left_ear",
          "x": 139.04913330078125,
          "y": 171.67526245117188,
          "confidence": 0.9659588932991028,
          "visible": true
        },
        {
          "name": "right_ear",
          "x": 119.55095672607422,
          "y": 173.77352905273438,
          "confidence": 0.03383443132042885,
          "visible": false
        },
        {
          "name": "left_shoulder",
          "x": 197.4403839111328,
          "y": 201.3944091796875,
          "confidence": 0.9864755272865295,
          "visible": true
        },
        {
          "name": "right_shoulder",
          "x": 174.52157592773438,
          "y": 193.92478942871094,
          "confidence": 0.8506630063056946,
          "visible": true
        },
        {
          "name": "left_elbow",
          "x": 243.53634643554688,
          "y": 267.71051025390625,
          "confidence": 0.9444326758384705,
          "visible": true
        },
        {
          "name": "right_elbow",
          "x": 207.57968139648438,
          "y": 241.2386016845703,
          "confidence": 0.4837872087955475,
          "visible": false
        },
        {
          "name": "left_wrist",
          "x": 237.9385223388672,
          "y": 289.12286376953125,
          "confidence": 0.9366744160652161,
          "visible": true
        },
        {
          "name": "right_wrist",
          "x": 215.50442504882812,
          "y": 267.8133544921875,
          "confidence": 0.5986645221710205,
          "visible": true
        },
        {
          "name": "left_hip",
          "x": 257.34429931640625,
          "y": 300.9150390625,
          "confidence": 0.963397204875946,
          "visible": true
        },
        {
          "name": "right_hip",
          "x": 243.353759765625,
          "y": 290.578857421875,
          "confidence": 0.9143566489219666,
          "visible": true
        },
        {
          "name": "left_knee",
          "x": 137.92141723632812,
          "y": 316.97216796875,
          "confidence": 0.9842476844787598,
          "visible": true
        },
        {
          "name": "right_knee",
          "x": 129.36720275878906,
          "y": 301.1103820800781,
          "confidence": 0.95961993932724,
          "visible": true
        },
        {
          "name": "left_ankle",
          "x": 124.05442810058594,
          "y": 434.74554443359375,
          "confidence": 0.9567379951477051,
          "visible": true
        },
        {
          "name": "right_ankle",
          "x": 128.3397216796875,
          "y": 418.8226318359375,
          "confidence": 0.9309802651405334,
          "visible": true
        }
      ],
      "confidence_scores": [
        0.9722278118133545,
        0.9872855544090271,
        0.5894169807434082,
        0.9659588932991028,
        0.03383443132042885,
        0.9864755272865295,
        0.8506630063056946,
        0.9444326758384705,
        0.4837872087955475,
        0.9366744160652161,
        0.5986645221710205,
        0.963397204875946,
        0.9143566489219666,
        0.9842476844787598,
        0.95961993932724,
        0.9567379951477051,
        0.9309802651405334
      ],
      "average_confidence": 0.8269859274082324
    }
  ]
}