{
  "timestamp": "2025-11-01T23:28:08.621110",
  "image_shape": {
    "height": 480,
    "width": 640,
    "channels": 3
  },
  "num_persons_detected": 1,
  "persons": [
    {
      "person_id": 0,
      "keypoints": [
        {
          "name": "nose",
          "x": 303.6427917480469,
          "y": 61.979278564453125,
          "confidence": 0.9647139310836792,
          "visible": true
        },
        {
          "name": "left_eye",
          "x": 312.43792724609375,
          "y": 49.837158203125,
          "confidence": 0.9838874936103821,
          "visible": true
        },
        {
          "name": "right_eye",
          "x": 304.52294921875,
          "y": 50.668365478515625,
          "confidence": 0.28108087182044983,
          "visible": false
        },
        {
          "name": "left_ear",
          "x": 338.01141357421875,
          "y": 59.342193603515625,
          "confidence": 0.9606770277023315,
          "visible": true
        },
        {
          "name": "right_ear",
          "x": 322.4158020019531,
          "y": 57.42823791503906,
          "confidence": 0.018423540517687798,
          "visible": false
        },
        {
          "name": "left_shoulder",
          "x": 339.22021484375,
          "y": 127.86029052734375,
          "confidence": 0.9961189031600952,
          "visible": true
        },
        {
          "name": "right_shoulder",
          "x": 349.8168029785156,
          "y": 118.12844848632812,
          "confidence": 0.8434033989906311,
          "visible": true
        },
        {
          "name": "left_elbow",
          "x": 269.3780517578125,
          "y": 203.953857421875,
          "confidence": 0.9967537522315979,
          "visible": true
        },
        {
          "name": "right_elbow",
          "x": 294.5433349609375,
          "y": 190.9214630126953,
          "confidence": 0.4837031364440918,
          "visible": false
        },
        {
          "name": "left_wrist",
          "x": 190.69784545898438,
          "y": 231.90675354003906,
          "confidence": 0.9966214895248413,
          "visible": true
        },
        {
          "name": "right_wrist",
          "x": 216.88018798828125,
          "y": 222.56817626953125,
          "confidence": 0.7964146137237549,
          "visible": true
        },
        {
          "name": "left_hip",
          "x": 309.31182861328125,
          "y": 265.681396484375,
          "confidence": 0.9925665855407715,
          "visible": true
        },
        {
          "name": "right_hip",
          "x": 315.48187255859375,
          "y": 250.97654724121094,
          "confidence": 0.945824921131134,
          "visible": true
        },
        {
          "name": "left_knee",
          "x": 178.11965942382812,
          "y": 264.0931396484375,
          "confidence": 0.9960899949073792,
          "visible": true
        },
        {
          "name": "right_knee",
          "x": 188.98355102539062,
          "y": 253.37095642089844,
          "confidence": 0.9636227488517761,
          "visible": true
        },
        {
          "name": "left_ankle",
          "x": 132.00949096679688,
          "y": 393.11846923828125,
          "confidence": 0.9711994528770447,
          "visible": true
        },
        {
          "name": "right_ankle",
          "x": 127.81937408447266,
          "y": 384.41864013671875,
          "confidence": 0.891379714012146,
          "visible": true
        }
      ],
      "confidence_scores": [
        0.9647139310836792,
        0.9838874936103821,
        0.28108087182044983,
        0.9606770277023315,
        0.018423540517687798,
        0.9961189031600952,
        0.8434033989906311,
        0.9967537522315979,
        0.4837031364440918,
        0.9966214895248413,
        0.7964146137237549,
        0.9925665855407715,
        0.945824921131134,
        0.9960899949073792,
        0.9636227488517761,
        0.9711994528770447,
        0.891379714012146
      ],
      "average_confidence": 0.8283812691841055
    }
  ]
}