{
  "timestamp": "2025-11-01T23:27:30.219835",
  "image_shape": {
    "height": 480,
    "width": 640,
    "channels": 3
  },
  "num_persons_detected": 1,
  "persons": [
    {
      "person_id": 0,
      "keypoints": [
        {
          "name": "nose",
          "x": 286.39239501953125,
          "y": 46.29515075683594,
          "confidence": 0.911029577255249,
          "visible": true
        },
        {
          "name": "left_eye",
          "x": 297.8308410644531,
          "y": 35.00105285644531,
          "confidence": 0.9534761905670166,
          "visible": true
        },
        {
          "name": "right_eye",
          "x": 291.8563232421875,
          "y": 39.163482666015625,
          "confidence": 0.17998705804347992,
          "visible": false
        },
        {
          "name": "left_ear",
          "x": 329.97137451171875,
          "y": 44.11714172363281,
          "confidence": 0.956026017665863,
          "visible": true
        },
        {
          "name": "right_ear",
          "x": 315.0024719238281,
          "y": 46.836395263671875,
          "confidence": 0.022482965141534805,
          "visible": false
        },
        {
          "name": "left_shoulder",
          "x": 315.5954895019531,
          "y": 114.09660339355469,
          "confidence": 0.9907225370407104,
          "visible": true
        },
        {
          "name": "right_shoulder",
          "x": 326.257080078125,
          "y": 108.25173950195312,
          "confidence": 0.8461468815803528,
          "visible": true
        },
        {
          "name": "left_elbow",
          "x": 264.44744873046875,
          "y": 213.36654663085938,
          "confidence": 0.9935604333877563,
          "visible": true
        },
        {
          "name": "right_elbow",
          "x": 282.85198974609375,
          "y": 194.03005981445312,
          "confidence": 0.3907296061515808,
          "visible": false
        },
        {
          "name": "left_wrist",
          "x": 177.70655822753906,
          "y": 262.37921142578125,
          "confidence": 0.9929186701774597,
          "visible": true
        },
        {
          "name": "right_wrist",
          "x": 205.24623107910156,
          "y": 251.7895965576172,
          "confidence": 0.6358471512794495,
          "visible": true
        },
        {
          "name": "left_hip",
          "x": 290.7950439453125,
          "y": 284.4322509765625,
          "confidence": 0.9857004880905151,
          "visible": true
        },
        {
          "name": "right_hip",
          "x": 296.1817932128906,
          "y": 272.4134521484375,
          "confidence": 0.9177144765853882,
          "visible": true
        },
        {
          "name": "left_knee",
          "x": 173.80853271484375,
          "y": 303.2646484375,
          "confidence": 0.9848498106002808,
          "visible": true
        },
        {
          "name": "right_knee",
          "x": 184.95541381835938,
          "y": 291.4371337890625,
          "confidence": 0.8770924806594849,
          "visible": true
        },
        {
          "name": "left_ankle",
          "x": 287.3939514160156,
          "y": 388.597412109375,
          "confidence": 0.8781142830848694,
          "visible": true
        },
        {
          "name": "right_ankle",
          "x": 270.9870300292969,
          "y": 378.4315490722656,
          "confidence": 0.6405792236328125,
          "visible": true
        }
      ],
      "confidence_scores": [
        0.911029577255249,
        0.9534761905670166,
        0.17998705804347992,
        0.956026017665863,
        0.022482965141534805,
        0.9907225370407104,
        0.8461468815803528,
        0.9935604333877563,
        0.3907296061515808,
        0.9929186701774597,
        0.6358471512794495,
        0.9857004880905151,
        0.9177144765853882,
        0.9848498106002808,
        0.8770924806594849,
        0.8781142830848694,
        0.6405792236328125
      ],
      "average_confidence": 0.7739398735849297
    }
  ]
}