{
  "timestamp": "2025-11-01T23:29:06.970861",
  "image_shape": {
    "height": 480,
    "width": 640,
    "channels": 3
  },
  "num_persons_detected": 1,
  "persons": [
    {
      "person_id": 0,
      "keypoints": [
        {
          "name": "nose",
          "x": 383.3983154296875,
          "y": 100.1375732421875,
          "confidence": 0.9766790866851807,
          "visible": true
        },
        {
          "name": "left_eye",
          "x": 395.3946228027344,
          "y": 91.54571533203125,
          "confidence": 0.9837949275970459,
          "visible": true
        },
        {
          "name": "right_eye",
          "x": 385.4353942871094,
          "y": 91.48031616210938,
          "confidence": 0.48399147391319275,
          "visible": false
        },
        {
          "name": "left_ear",
          "x": 417.42999267578125,
          "y": 109.55630493164062,
          "confidence": 0.9491971731185913,
          "visible": true
        },
        {
          "name": "right_ear",
          "x": 395.1301574707031,
          "y": 106.80412292480469,
          "confidence": 0.04022129997611046,
          "visible": false
        },
        {
          "name": "left_shoulder",
          "x": 400.6932678222656,
          "y": 170.68753051757812,
          "confidence": 0.9956598877906799,
          "visible": true
        },
        {
          "name": "right_shoulder",
          "x": 393.8818359375,
          "y": 161.66421508789062,
          "confidence": 0.9098553657531738,
          "visible": true
        },
        {
          "name": "left_elbow",
          "x": 321.6944885253906,
          "y": 222.2328338623047,
          "confidence": 0.9968345761299133,
          "visible": true
        },
        {
          "name": "right_elbow",
          "x": 324.18328857421875,
          "y": 210.2892608642578,
          "confidence": 0.6650340557098389,
          "visible": true
        },
        {
          "name": "left_wrist",
          "x": 231.25921630859375,
          "y": 242.73635864257812,
          "confidence": 0.9974108338356018,
          "visible": true
        },
        {
          "name": "right_wrist",
          "x": 248.24163818359375,
          "y": 235.9586639404297,
          "confidence": 0.8773531913757324,
          "visible": true
        },
        {
          "name": "left_hip",
          "x": 322.48114013671875,
          "y": 293.04339599609375,
          "confidence": 0.992572009563446,
          "visible": true
        },
        {
          "name": "right_hip",
          "x": 316.12054443359375,
          "y": 276.8033447265625,
          "confidence": 0.9571330547332764,
          "visible": true
        },
        {
          "name": "left_knee",
          "x": 184.53379821777344,
          "y": 280.2619323730469,
          "confidence": 0.9940154552459717,
          "visible": true
        },
        {
          "name": "right_knee",
          "x": 188.51121520996094,
          "y": 269.64935302734375,
          "confidence": 0.9530541300773621,
          "visible": true
        },
        {
          "name": "left_ankle",
          "x": 164.8845977783203,
          "y": 418.0900573730469,
          "confidence": 0.9481855630874634,
          "visible": true
        },
        {
          "name": "right_ankle",
          "x": 161.2411346435547,
          "y": 410.0027770996094,
          "confidence": 0.8247332572937012,
          "visible": true
        }
      ],
      "confidence_scores": [
        0.9766790866851807,
        0.9837949275970459,
        0.48399147391319275,
        0.9491971731185913,
        0.04022129997611046,
        0.9956598877906799,
        0.9098553657531738,
        0.9968345761299133,
        0.6650340557098389,
        0.9974108338356018,
        0.8773531913757324,
        0.992572009563446,
        0.9571330547332764,
        0.9940154552459717,
        0.9530541300773621,
        0.9481855630874634,
        0.8247332572937012
      ],
      "average_confidence": 0.855630902463899
    }
  ]
}